cengal_app_dir_path_finder/__init__.py
cengal_app_dir_path_finder/versions/__init__.py
cengal_app_dir_path_finder/versions/v_0/__init__.py
cengal_app_dir_path_finder-1.1.1.dist-info/METADATA
cengal_app_dir_path_finder-1.1.1.dist-info/WHEEL
cengal_app_dir_path_finder-1.1.1.dist-info/licenses/LICENSE.md
cengal_app_dir_path_finder-1.1.1.dist-info/licenses/NOTICE
cengal_app_dir_path_finder-1.1.1.dist-info/RECORD
